autonbox/NHITS.py
autonbox/__init__.py
autonbox/autoARIMA_wrapper.py
autonbox/clean_augment.py
autonbox/iterative_labeling.py
autonbox/merge_partial_multipredictions.py
autonbox/resnext101_kinetics_video_features.py
autonbox/contrib/__init__.py
autonbox/contrib/resnet/__init__.py
autonbox/contrib/resnet/dataset.py
autonbox/contrib/resnet/model.py
autonbox/contrib/resnet/spatial_transforms.py
autonbox/contrib/resnet/temporal_transforms.py
autonbox/contrib/resnet/models/__init__.py
autonbox/contrib/resnet/models/densenet.py
autonbox/contrib/resnet/models/pre_act_resnet.py
autonbox/contrib/resnet/models/resnet.py
autonbox/contrib/resnet/models/resnext.py
autonbox/contrib/resnet/models/wide_resnet.py
autonbox-0.3.0.dist-info/LICENSE
autonbox-0.3.0.dist-info/METADATA
autonbox-0.3.0.dist-info/WHEEL
autonbox-0.3.0.dist-info/entry_points.txt
autonbox-0.3.0.dist-info/top_level.txt
autonbox-0.3.0.dist-info/RECORD
