Metadata-Version: 2.1
Name: autonbox
Version: 0.3.0
Summary: Auton Lab TA1 primitives
Home-page: https://github.com/autonlab/autonbox
Author: CMU
Author-email: awillia2@andrew.cmu.edu
License: MIT
Classifier: Programming Language :: Python :: 3
Classifier: License :: OSI Approved :: MIT License
Classifier: Operating System :: OS Independent
License-File: LICENSE
Requires-Dist: d3m
Requires-Dist: Pillow (>=7.1.2)
Requires-Dist: numpy
Requires-Dist: pandas
Requires-Dist: opencv-python-headless
Requires-Dist: torch (>=1.4.0)
Requires-Dist: torchvision (>=0.5.0)
Requires-Dist: statsforecast
Requires-Dist: neuralforecast (>=1.3.0)
Requires-Dist: transformers (>=4.6.0)
